Workbook

Sheet Objectifs et KPI
A1: CASA NOVA – Objectifs opérationnels et choix des KPI (questions 1 à 3)
A3: Q1 – Trois objectifs opérationnels à piloter en septembre
A4: 1. Augmenter le CA TTC de 105 894 € (août) à 112 000 € en septembre, soit +5,8 %, en convertissant mieux le trafic plutôt qu'en comptant sur sa seule hausse.
A5: 2. Améliorer l'efficacité commerciale : porter le taux de transformation de 27 % à 28 % et maintenir un panier moyen d'au moins 53 € avec 2,10 articles par ticket.
A6: 3. Restaurer l'expérience client : CSAT ≥ 90 %, NPS ≥ 35 points et CES ≥ 5,5 / 7 en septembre.
A8: Q2 et Q3 – KPI retenus, objectif suivi, intérêt pour le manager et classement
A9: KPI | B9: Calcul | C9: Objectif suivi | D9: Intérêt pour le manager | E9: Famille (Q3)
A10: CA TTC | B10: Somme des ventes TTC du mois | C10: 112 000 € | D10: Mesure le résultat global de l'unité commerciale et sa progression. | E10: Résultat commercial
A11: Taux de transformation | B11: Tickets / visiteurs | C11: 28 % | D11: Montre la capacité à convertir les visiteurs en acheteurs (accueil, conseil, disponibilité des vendeurs). | E11: Efficacité commerciale
A12: Panier moyen | B12: CA TTC / tickets | C12: 53 € | D12: Mesure la valeur d'un achat ; levier sur le CA sans besoin de trafic supplémentaire. | E12: Efficacité commerciale
A13: Indice des ventes | B13: Articles vendus / tickets | C13: 2,10 | D13: Mesure la vente additionnelle et complémentaire (articles par client). | E13: Efficacité commerciale
A14: CSAT | B14: % de clients satisfaits | C14: 90 % | D14: Mesure la satisfaction immédiate après l'achat. | E14: Satisfaction client
A15: NPS | B15: % promoteurs − % détracteurs | C15: 35 pts | D15: Mesure la recommandation et la fidélité future (bouche-à-oreille). | E15: Satisfaction client
A16: CES moyen | B16: Score d'effort de 1 à 7 | C16: 5,5 / 7 | D16: Mesure la facilité du parcours d'achat (attente, caisse, SAV). | E16: Satisfaction client
A18: Indicateurs de contexte suivis sans objectif : visiteurs (trafic), tickets, prix moyen par article.

Sheet Tableau de bord
A1: CASA NOVA – Tableau de bord commercial · septembre
A2: Réunion commerciale · période de référence : août · sources : données brutes et enquête de satisfaction
A4: KPI sélectionné | B4: Objectif | C4: Réalisé sept. | D4: Réalisé août | E4: Écart objectif | F4: Évolution août/sept. | G4: Statut / décision | H4: Famille de KPI
A5: CA TTC | B5: =Calculs!B21 | C5: =Calculs!C21 | D5: ='Données brutes'!E5 | E5: =Calculs!D21 | F5: =('Données brutes'!E6-'Données brutes'!E5)/'Données brutes'!E5 | G5: =IF(C5>=B5,"✔ Atteint","✘ Non atteint")&" – "&"Croissance portée par le trafic : à consolider" | H5: Résultat commercial
A6: Taux de transformation | B6: =Calculs!B22 | C6: =Calculs!C22 | D6: ='Données brutes'!I5 | E6: =Calculs!D22 | F6: =('Données brutes'!I6-'Données brutes'!I5)*100 | G6: =IF(C6>=B6,"✔ Atteint","✘ Non atteint")&" – "&"Prioritaire : accueil et conseil en magasin" | H6: Efficacité commerciale
A7: Panier moyen | B7: =Calculs!B23 | C7: =Calculs!C23 | D7: ='Données brutes'!J5 | E7: =Calculs!D23 | F7: ='Données brutes'!J6-'Données brutes'!J5 | G7: =IF(C7>=B7,"✔ Atteint","✘ Non atteint")&" – "&"Hausse due au prix moyen, pas au nombre d'articles" | H7: Efficacité commerciale
A8: Indice des ventes | B8: =Calculs!B24 | C8: =Calculs!C24 | D8: ='Données brutes'!K5 | E8: =Calculs!D24 | F8: ='Données brutes'!K6-'Données brutes'!K5 | G8: =IF(C8>=B8,"✔ Atteint","✘ Non atteint")&" – "&"Relancer la vente additionnelle" | H8: Efficacité commerciale
A9: CSAT | B9: =Calculs!B25 | C9: =Calculs!C25 | D9: ='Données brutes'!F5 | E9: =Calculs!D25 | F9: ='Données brutes'!F6-'Données brutes'!F5 | G9: =IF(C9>=B9,"✔ Atteint","✘ Non atteint")&" – "&"Alerte : en baisse chaque mois depuis mai (91 % → 81 %)" | H9: Satisfaction client
A10: NPS | B10: =Calculs!B26 | C10: =Calculs!C26 | D10: ='Données brutes'!G5 | E10: =Calculs!D26 | F10: ='Données brutes'!G6-'Données brutes'!G5 | G10: =IF(C10>=B10,"✔ Atteint","✘ Non atteint")&" – "&"Alerte : détracteurs en forte hausse (28 %)" | H10: Satisfaction client
A11: CES moyen /7 | B11: =Calculs!B27 | C11: =Calculs!C27 | D11: ='Données brutes'!H5 | E11: =Calculs!D27 | F11: ='Données brutes'!H6-'Données brutes'!H5 | G11: =IF(C11>=B11,"✔ Atteint","✘ Non atteint")&" – "&"Simplifier le parcours (attente, caisse)" | H11: Satisfaction client
A12: Lecture : écart objectif en € (CA, panier), en points de % (taux de transformation, CSAT), en points de score (NPS, CES). Évolution août/sept. : relative (%) pour le CA, en valeur ou en points pour les autres.
A13: Indicateurs de contexte
A14: Visiteurs (trafic) | B14: — | C14: ='Données brutes'!B6 | D14: ='Données brutes'!B5 | E14: — | F14: =('Données brutes'!B6-'Données brutes'!B5)/'Données brutes'!B5 | G14: Trafic en forte hausse (+8,1 %) | H14: Contexte
A15: Tickets | B15: — | C15: ='Données brutes'!C6 | D15: ='Données brutes'!C5 | E15: — | F15: =('Données brutes'!C6-'Données brutes'!C5)/'Données brutes'!C5 | G15: Tickets quasi stables malgré le trafic | H15: Contexte
A16: Prix moyen par article | B16: — | C16: ='Données brutes'!L6 | D16: ='Données brutes'!L5 | E16: — | F16: =('Données brutes'!L6-'Données brutes'!L5)/'Données brutes'!L5 | G16: Hausse du prix moyen : effet prix/gamme à vérifier | H16: Contexte

Sheet Données brutes
A1: Période | B1: Visiteurs | C1: Tickets | D1: Articles vendus | E1: CA TTC (€) | F1: CSAT (%) | G1: NPS (points) | H1: CES moyen /7 | I1: Taux de transformation | J1: Panier moyen (€) | K1: Indice des ventes | L1: Prix moyen article (€) | M1: NPS recalculé (enquête)
A2: Mai | B2: 6200 | C2: 1860 | D2: 3906 | E2: 93000 | F2: 91 | G2: 42 | H2: 5.8 | I2: =C2/B2 | J2: =E2/C2 | K2: =D2/C2 | L2: =E2/D2 | M2: ='Enquête satisfaction'!B2-'Enquête satisfaction'!C2
A3: Juin | B3: 6600 | C3: 1914 | D3: 4019 | E3: 97614 | F3: 90 | G3: 39 | H3: 5.7 | I3: =C3/B3 | J3: =E3/C3 | K3: =D3/C3 | L3: =E3/D3 | M3: ='Enquête satisfaction'!B3-'Enquête satisfaction'!C3
A4: Juillet | B4: 7100 | C4: 1988 | D4: 4175 | E4: 103376 | F4: 88 | G4: 34 | H4: 5.4 | I4: =C4/B4 | J4: =E4/C4 | K4: =D4/C4 | L4: =E4/D4 | M4: ='Enquête satisfaction'!B4-'Enquête satisfaction'!C4
A5: Août | B5: 7400 | C5: 1998 | D5: 4196 | E5: 105894 | F5: 85 | G5: 25 | H5: 5 | I5: =C5/B5 | J5: =E5/C5 | K5: =D5/C5 | L5: =E5/D5 | M5: ='Enquête satisfaction'!B5-'Enquête satisfaction'!C5
A6: Septembre | B6: 8000 | C6: 2000 | D6: 4000 | E6: 110000 | F6: 81 | G6: 16 | H6: 4.6 | I6: =C6/B6 | J6: =E6/C6 | K6: =D6/C6 | L6: =E6/D6 | M6: ='Enquête satisfaction'!B6-'Enquête satisfaction'!C6
A9: OBJECTIFS SEPTEMBRE | B9: Valeur | C9: Source : annexe 2 du sujet
A10: CA TTC (€) | B10: 112000
A11: Taux transformation (%) | B11: 0.28
A12: Panier moyen (€) | B12: 53
A13: Indice des ventes | B13: 2.1
A14: CSAT (%) | B14: 90
A15: NPS (points) | B15: 35
A16: CES cible /7 | B16: 5.5
A17: Période de référence | B17: Août
A19: Formules : taux de transformation = tickets / visiteurs ; panier moyen = CA TTC / tickets ; indice des ventes = articles / tickets ; prix moyen article = CA TTC / articles ; NPS = % promoteurs − % détracteurs.
A20: Cellules bleu clair = calculées par formule.

Sheet Calculs
A1: CASA NOVA – Calculs (questions 4 à 7)
A2: Toutes les valeurs sont calculées par formules à partir de la feuille « Données brutes » (août = ligne 5, septembre = ligne 6).
A4: Q4 – Indicateurs d'efficacité commerciale
A5: Indicateur | B5: Formule | C5: Août | D5: Septembre | E5: Objectif sept.
A6: Taux de transformation | B6: Tickets / Visiteurs | C6: ='Données brutes'!I5 | D6: ='Données brutes'!I6 | E6: ='Données brutes'!B11
A7: Panier moyen | B7: CA TTC / Tickets | C7: ='Données brutes'!J5 | D7: ='Données brutes'!J6 | E7: ='Données brutes'!B12
A8: Indice des ventes (articles / ticket) | B8: Articles vendus / Tickets | C8: ='Données brutes'!K5 | D8: ='Données brutes'!K6 | E8: ='Données brutes'!B13
A9: Prix moyen par article | B9: CA TTC / Articles vendus | C9: ='Données brutes'!L5 | D9: ='Données brutes'!L6 | E9: —
A12: Q5 – Évolution août → septembre
A13: Indicateur | B13: Août | C13: Septembre | D13: Écart en valeur | E13: Évolution relative (%)
A14: Chiffre d'affaires TTC | B14: ='Données brutes'!E5 | C14: ='Données brutes'!E6 | D14: =C14-B14 | E14: =(C14-B14)/B14
A15: Trafic (visiteurs) | B15: ='Données brutes'!B5 | C15: ='Données brutes'!B6 | D15: =C15-B15 | E15: =(C15-B15)/B15
A16: Nombre de tickets | B16: ='Données brutes'!C5 | C16: ='Données brutes'!C6 | D16: =C16-B16 | E16: =(C16-B16)/B16
A17: Évolution relative = (septembre − août) / août (la différence est rapportée à la valeur de départ).
A19: Q6 – Écarts réalisé septembre / objectif
A20: Indicateur | B20: Objectif | C20: Réalisé sept. | D20: Écart | E20: Unité de l'écart | F20: Écart relatif | G20: Objectif atteint ?
A21: CA TTC | B21: ='Données brutes'!B10 | C21: ='Données brutes'!E6 | D21: =C21-B21 | E21: euros | F21: =(C21-B21)/B21 | G21: =IF(C21>=B21,"Oui","Non")
A22: Taux de transformation | B22: ='Données brutes'!B11 | C22: ='Données brutes'!I6 | D22: =(C22-B22)*100 | E22: points de % | F22: =(C22-B22)/B22 | G22: =IF(C22>=B22,"Oui","Non")
A23: Panier moyen | B23: ='Données brutes'!B12 | C23: ='Données brutes'!J6 | D23: =C23-B23 | E23: euros | F23: =(C23-B23)/B23 | G23: =IF(C23>=B23,"Oui","Non")
A24: Indice des ventes | B24: ='Données brutes'!B13 | C24: ='Données brutes'!K6 | D24: =C24-B24 | E24: articles / ticket | F24: =(C24-B24)/B24 | G24: =IF(C24>=B24,"Oui","Non")
A25: CSAT | B25: ='Données brutes'!B14 | C25: ='Données brutes'!F6 | D25: =C25-B25 | E25: points de % | F25: =(C25-B25)/B25 | G25: =IF(C25>=B25,"Oui","Non")
A26: NPS | B26: ='Données brutes'!B15 | C26: ='Données brutes'!G6 | D26: =C26-B26 | E26: points de score NPS | F26: =(C26-B26)/B26 | G26: =IF(C26>=B26,"Oui","Non")
A27: CES moyen /7 | B27: ='Données brutes'!B16 | C27: ='Données brutes'!H6 | D27: =C27-B27 | E27: points de score (/7) | F27: =(C27-B27)/B27 | G27: =IF(C27>=B27,"Oui","Non")
A28: Taux et CSAT : écart en points de pourcentage (pts). NPS : points de score (de −100 à +100). CES : points sur l'échelle de 1 à 7 (un score élevé est favorable).
A30: Q7 – Contrôle de cohérence : CA reconstitué = tickets × panier moyen
A31: Mois | B31: Tickets | C31: Panier moyen | D31: CA reconstitué | E31: CA réel | F31: Écart | G31: Cohérent ?
A32: Août | B32: ='Données brutes'!C5 | C32: ='Données brutes'!J5 | D32: =B32*C32 | E32: ='Données brutes'!E5 | F32: =ROUND(D32-E32,2) | G32: =IF(ABS(F32)<0.01,"Oui","Non")
A33: Septembre | B33: ='Données brutes'!C6 | C33: ='Données brutes'!J6 | D33: =B33*C33 | E33: ='Données brutes'!E6 | F33: =ROUND(D33-E33,2) | G33: =IF(ABS(F33)<0.01,"Oui","Non")
A34: Le CA reconstitué est égal au CA réel : les indicateurs calculés sont cohérents entre eux (CA = visiteurs × taux de transformation × panier moyen).

Sheet Enquête satisfaction
A1: Mois | B1: Promoteurs (%) | C1: Détracteurs (%) | D1: Passifs (%) | E1: NPS (pts) = promoteurs − détracteurs | F1: Contrôle (promo + détrac + passifs)
A2: Mai | B2: 59 | C2: 17 | D2: 24 | E2: =B2-C2 | F2: =B2+C2+D2
A3: Juin | B3: 57 | C3: 18 | D3: 25 | E3: =B3-C3 | F3: =B3+C3+D3
A4: Juillet | B4: 54 | C4: 20 | D4: 26 | E4: =B4-C4 | F4: =B4+C4+D4
A5: Août | B5: 48 | C5: 23 | D5: 29 | E5: =B5-C5 | F5: =B5+C5+D5
A6: Septembre | B6: 44 | C6: 28 | D6: 28 | E6: =B6-C6 | F6: =B6+C6+D6
