Workbook

Sheet Données brutes
A1: Période | B1: Visiteurs | C1: Tickets | D1: Articles vendus | E1: CA TTC (€) | F1: CSAT (%) | G1: NPS (points) | H1: CES moyen /7 | I1: Taux de transformation | J1: Panier moyen (€) | K1: Indice des ventes | L1: Prix moyen article (€)
A2: Mai | B2: 6200 | C2: 1860 | D2: 3906 | E2: 93000 | F2: 91 | G2: 42 | H2: 5.8 | I2: =C2/B2 | J2: =E2/C2 | K2: =D2/C2 | L2: =E2/D2
A3: Juin | B3: 6600 | C3: 1914 | D3: 4019 | E3: 97614 | F3: 90 | G3: 39 | H3: 5.7 | I3: =C3/B3 | J3: =E3/C3 | K3: =D3/C3 | L3: =E3/D3
A4: Juillet | B4: 7100 | C4: 1988 | D4: 4175 | E4: 103376 | F4: 88 | G4: 34 | H4: 5.4 | I4: =C4/B4 | J4: =E4/C4 | K4: =D4/C4 | L4: =E4/D4
A5: Août | B5: 7400 | C5: 1998 | D5: 4196 | E5: 105894 | F5: 85 | G5: 25 | H5: 5 | I5: =C5/B5 | J5: =E5/C5 | K5: =D5/C5 | L5: =E5/D5
A6: Septembre | B6: 8000 | C6: 2000 | D6: 4000 | E6: 110000 | F6: 81 | G6: 16 | H6: 4.6 | I6: =C6/B6 | J6: =E6/C6 | K6: =D6/C6 | L6: =E6/D6
A9: OBJECTIFS SEPTEMBRE | B9: Valeur | D9: ÉVOLUTION AOÛT → SEPT. (Q5) | E9: Écart | F9: Évolution % | H9: CONTRÔLE (Q7) | I9: CA reconstitué | J9: CA réel | K9: Écart
A10: CA TTC (€) | B10: 112000 | D10: CA TTC (€) | E10: =E6-E5 | F10: =(E6-E5)/E5 | H10: Août | I10: =C5*J5 | J10: =E5 | K10: =I10-J10
A11: Taux transformation (%) | B11: 0.28 | D11: Visiteurs | E11: =B6-B5 | F11: =(B6-B5)/B5 | H11: Septembre | I11: =C6*J6 | J11: =E6 | K11: =I11-J11
A12: Panier moyen (€) | B12: 53 | D12: Tickets | E12: =C6-C5 | F12: =(C6-C5)/C5 | H12: Tickets × panier moyen = CA réel : les calculs sont cohérents.
A13: Indice des ventes | B13: 2.1
A14: CSAT (%) | B14: 90
A15: NPS (points) | B15: 35
A16: CES cible /7 | B16: 5.5
A17: Période de référence | B17: Août

Sheet Tableau de bord à créer
A1: KPI sélectionné | B1: Objectif | C1: Réalisé sept. | D1: Réalisé août | E1: Écart objectif | F1: Évolution août/sept. | G1: Statut / décision
A2: CA TTC (€) | B2: ='Données brutes'!B10 | C2: ='Données brutes'!E6 | D2: ='Données brutes'!E5 | E2: =C2-B2 | F2: =(C2-D2)/D2 | G2: =IF(C2>=B2,"Atteint","Non atteint")
A3: Taux de transformation | B3: ='Données brutes'!B11 | C3: ='Données brutes'!I6 | D3: ='Données brutes'!I5 | E3: =(C3-B3)*100 | F3: =(C3-D3)*100 | G3: =IF(C3>=B3,"Atteint","Non atteint")
A4: Panier moyen (€) | B4: ='Données brutes'!B12 | C4: ='Données brutes'!J6 | D4: ='Données brutes'!J5 | E4: =C4-B4 | F4: =C4-D4 | G4: =IF(C4>=B4,"Atteint","Non atteint")
A5: Indice des ventes | B5: ='Données brutes'!B13 | C5: ='Données brutes'!K6 | D5: ='Données brutes'!K5 | E5: =C5-B5 | F5: =C5-D5 | G5: =IF(C5>=B5,"Atteint","Non atteint")
A6: CSAT (%) | B6: ='Données brutes'!B14 | C6: ='Données brutes'!F6 | D6: ='Données brutes'!F5 | E6: =C6-B6 | F6: =C6-D6 | G6: =IF(C6>=B6,"Atteint","Non atteint")
A7: NPS (points) | B7: ='Données brutes'!B15 | C7: ='Données brutes'!G6 | D7: ='Données brutes'!G5 | E7: =C7-B7 | F7: =C7-D7 | G7: =IF(C7>=B7,"Atteint","Non atteint")
A8: CES moyen /7 | B8: ='Données brutes'!B16 | C8: ='Données brutes'!H6 | D8: ='Données brutes'!H5 | E8: =C8-B8 | F8: =C8-D8 | G8: =IF(C8>=B8,"Atteint","Non atteint")
A10: Écarts : en € pour le CA et le panier, en points de % pour le taux de transformation et le CSAT, en points de score pour le NPS et le CES. Évolution : en % pour le CA, en points/valeur pour les autres.

Sheet Enquête satisfaction
A1: Mois | B1: Promoteurs (%) | C1: Détracteurs (%) | D1: Passifs (%) | E1: NPS (points)
A2: Mai | B2: 59 | C2: 17 | D2: 24 | E2: =B2-C2
A3: Juin | B3: 57 | C3: 18 | D3: 25 | E3: =B3-C3
A4: Juillet | B4: 54 | C4: 20 | D4: 26 | E4: =B4-C4
A5: Août | B5: 48 | C5: 23 | D5: 29 | E5: =B5-C5
A6: Septembre | B6: 44 | C6: 28 | D6: 28 | E6: =B6-C6
